{
  "$schema": "https://developer.microsoft.com/json-schemas/fabric/item/report/definition/visualContainer/2.8.0/schema.json",
  "name": "3fa36bcac51146d090de",
  "position": {
    "x": 606.58634538152614,
    "y": 30.843373493975903,
    "z": 5000,
    "height": 62.714859437751,
    "width": 206.65060240963857,
    "tabOrder": 5000
  },
  "visual": {
    "visualType": "card",
    "query": {
      "queryState": {
        "Values": {
          "projections": [
            {
              "field": {
                "Measure": {
                  "Expression": {
                    "SourceRef": {
                      "Entity": "_medidas"
                    }
                  },
                  "Property": "Valor Pedidos Total Periodo"
                }
              },
              "queryRef": "_medidas.Valor Pedidos Total Periodo",
              "nativeQueryRef": "Valor Pedidos Total Periodo"
            }
          ]
        }
      },
      "sortDefinition": {
        "sort": [
          {
            "field": {
              "Measure": {
                "Expression": {
                  "SourceRef": {
                    "Entity": "_medidas"
                  }
                },
                "Property": "Valor Pedidos Total Periodo"
              }
            },
            "direction": "Descending"
          }
        ],
        "isDefaultSort": true
      }
    },
    "objects": {
      "categoryLabels": [
        {
          "properties": {
            "show": {
              "expr": {
                "Literal": {
                  "Value": "true"
                }
              }
            },
            "fontSize": {
              "expr": {
                "Literal": {
                  "Value": "9D"
                }
              }
            },
            "color": {
              "solid": {
                "color": {
                  "expr": {
                    "ThemeDataColor": {
                      "ColorId": 0,
                      "Percent": 0
                    }
                  }
                }
              }
            }
          }
        }
      ],
      "labels": [
        {
          "properties": {
            "fontSize": {
              "expr": {
                "Literal": {
                  "Value": "17D"
                }
              }
            },
            "color": {
              "solid": {
                "color": {
                  "expr": {
                    "ThemeDataColor": {
                      "ColorId": 0,
                      "Percent": 0
                    }
                  }
                }
              }
            },
            "labelDisplayUnits": {
              "expr": {
                "Literal": {
                  "Value": "1D"
                }
              }
            }
          }
        }
      ]
    },
    "visualContainerObjects": {
      "background": [
        {
          "properties": {
            "show": {
              "expr": {
                "Literal": {
                  "Value": "false"
                }
              }
            },
            "transparency": {
              "expr": {
                "Literal": {
                  "Value": "0D"
                }
              }
            }
          }
        }
      ],
      "title": [
        {
          "properties": {
            "text": {
              "expr": {
                "Literal": {
                  "Value": "'valor ptax'"
                }
              }
            },
            "show": {
              "expr": {
                "Literal": {
                  "Value": "false"
                }
              }
            },
            "titleWrap": {
              "expr": {
                "Literal": {
                  "Value": "true"
                }
              }
            }
          }
        }
      ],
      "border": [
        {
          "properties": {
            "width": {
              "expr": {
                "Literal": {
                  "Value": "1D"
                }
              }
            }
          }
        }
      ]
    },
    "drillFilterOtherVisuals": true
  }
}